gpt_chat_mate/__init__.py
gpt_chat_mate/main.py
gpt_chat_mate-1.7.1.dist-info/LICENSE
gpt_chat_mate-1.7.1.dist-info/METADATA
gpt_chat_mate-1.7.1.dist-info/WHEEL
gpt_chat_mate-1.7.1.dist-info/entry_points.txt
gpt_chat_mate-1.7.1.dist-info/top_level.txt
gpt_chat_mate-1.7.1.dist-info/RECORD
