Metadata-Version: 2.1
Name: gpt-chat-mate
Version: 1.7.1
Summary: A cli app for communicating with chatGPT
Home-page: https://gitlab.com/fizzizist/gpt-chat-mate
Author: Fizzizist
Author-email: gpt-chat-mate@fizzizist.33mail.com
License: GPLv3
Platform: UNKNOWN
Classifier: Programming Language :: Python :: 3
Classifier: License :: OSI Approved :: GNU General Public License v3 (GPLv3)
Classifier: Operating System :: OS Independent
Requires-Python: >=3.6
Requires-Dist: func-timeout
Requires-Dist: openai
Requires-Dist: pyfiglet
Requires-Dist: pygments
Requires-Dist: tiktoken
